{"ndof": 36, "demangled": true, "vars": [{"name": "c", "subdomains": [{"id": 0, "kernels": [{"name": "cres", "type": "SplitCHParsed"}], "dofs": [0, 4, 8, 12, 16, 20, 24, 28, 32]}]}, {"name": "w", "subdomains": [{"id": 0, "kernels": [{"name": "wres", "type": "SplitCHWRes"}, {"name": "time", "type": "CoupledTimeDerivative"}], "dofs": [1, 5, 9, 13, 17, 21, 25, 29, 33]}]}, {"name": "gr0", "subdomains": [{"id": 0, "kernels": [{"name": "IE_gr0", "type": "TimeDerivative"}, {"name": "ACBulk_gr0", "type": "ACParticleGrowth"}, {"name": "ACInt_gr0", "type": "ACInterface"}], "dofs": [2, 6, 10, 14, 18, 22, 26, 30, 34]}]}, {"name": "gr1", "subdomains": [{"id": 0, "kernels": [{"name": "IE_gr1", "type": "TimeDerivative"}, {"name": "ACBulk_gr1", "type": "ACParticleGrowth"}, {"name": "ACInt_gr1", "type": "ACInterface"}], "dofs": [3, 7, 11, 15, 19, 23, 27, 31, 35]}]}]}

